<?xml version="1.0" encoding="UTF-8" standalone="yes"?>
<w:ftr xmlns:ve="http://schemas.openxmlformats.org/markup-compatibility/2006" xmlns:o="urn:schemas-microsoft-com:office:office" xmlns:r="http://schemas.openxmlformats.org/officeDocument/2006/relationships" xmlns:m="http://schemas.openxmlformats.org/officeDocument/2006/math" xmlns:v="urn:schemas-microsoft-com:vml" xmlns:wp="http://schemas.openxmlformats.org/drawingml/2006/wordprocessingDrawing" xmlns:w10="urn:schemas-microsoft-com:office:word" xmlns:w="http://schemas.openxmlformats.org/wordprocessingml/2006/main" xmlns:wne="http://schemas.microsoft.com/office/word/2006/wordml"><w:p w:rsidR="00445E78" w:rsidRDefault="00445E78" w:rsidP="00445E78"><w:pPr><w:pStyle w:val="a4"/><w:rPr><w:rFonts w:ascii="Times New Roman" w:hAnsi="Times New Roman"/><w:b/></w:rPr></w:pPr><w:r><w:rPr><w:rFonts w:ascii="Times New Roman" w:hAnsi="Times New Roman"/><w:b/></w:rPr><w:t>ПРОДАВЕЦ</w:t></w:r><w:r><w:rPr><w:rFonts w:ascii="Times New Roman" w:hAnsi="Times New Roman"/></w:rPr><w:t xml:space="preserve">: </w:t></w:r><w:r><w:rPr><w:rFonts w:ascii="Times New Roman" w:hAnsi="Times New Roman"/><w:b/></w:rPr><w:t>ООО «УралАвтоХаус»</w:t></w:r></w:p><w:p w:rsidR="00445E78" w:rsidRDefault="00445E78" w:rsidP="00445E78"><w:pPr><w:rPr><w:i/><w:iCs/><w:sz w:val="20"/></w:rPr></w:pPr><w:r><w:rPr><w:i/><w:iCs/><w:sz w:val="20"/></w:rPr><w:t xml:space="preserve">Юридический адрес: </w:t></w:r><w:smartTag w:uri="urn:schemas-microsoft-com:office:smarttags" w:element="metricconverter"><w:smartTagPr><w:attr w:name="ProductID" w:val="454012, г"/></w:smartTagPr><w:r><w:rPr><w:i/><w:iCs/><w:sz w:val="20"/></w:rPr><w:t>454012, г</w:t></w:r></w:smartTag><w:r><w:rPr><w:i/><w:iCs/><w:sz w:val="20"/></w:rPr><w:t>. Челябинск, ул. Горелова, 12</w:t></w:r></w:p><w:p w:rsidR="00445E78" w:rsidRDefault="00445E78" w:rsidP="00445E78"><w:pPr><w:rPr><w:i/><w:iCs/><w:sz w:val="20"/></w:rPr></w:pPr><w:r><w:rPr><w:i/><w:iCs/><w:sz w:val="20"/></w:rPr><w:t>ИНН 7449023616 / КПП 744901001</w:t></w:r></w:p><w:p w:rsidR="00445E78" w:rsidRDefault="00445E78" w:rsidP="00445E78"><w:pPr><w:rPr><w:i/><w:iCs/><w:sz w:val="20"/></w:rPr></w:pPr><w:r><w:rPr><w:i/><w:iCs/><w:sz w:val="20"/></w:rPr><w:t>Р/с 40702810272020102062 в Челябинском отделении N 8597 г. Челябинск</w:t></w:r></w:p><w:p w:rsidR="00445E78" w:rsidRDefault="00445E78" w:rsidP="00445E78"><w:pPr><w:rPr><w:i/><w:iCs/><w:sz w:val="20"/></w:rPr></w:pPr><w:r><w:rPr><w:i/><w:iCs/><w:sz w:val="20"/></w:rPr><w:t>К/с 30101810700000000602, БИК 047501602</w:t></w:r></w:p><w:p w:rsidR="00445E78" w:rsidRDefault="00445E78" w:rsidP="00445E78"><w:pPr><w:pStyle w:val="a4"/><w:rPr><w:rFonts w:ascii="Times New Roman" w:hAnsi="Times New Roman"/><w:b/></w:rPr></w:pPr></w:p><w:p w:rsidR="00445E78" w:rsidRPr="004A6D87" w:rsidRDefault="00445E78" w:rsidP="00445E78"><w:pPr><w:pStyle w:val="a4"/><w:rPr><w:rFonts w:ascii="Times New Roman" w:hAnsi="Times New Roman"/><w:b/></w:rPr></w:pPr><w:r w:rsidRPr="004A6D87"><w:rPr><w:rFonts w:ascii="Times New Roman" w:hAnsi="Times New Roman"/><w:b/></w:rPr><w:t xml:space="preserve">ПОКУПАТЕЛЬ: </w:t></w:r><w:fldSimple w:instr=" DOCPROPERTY  person_name  \* MERGEFORMAT "><w:r w:rsidR="004A6D87" w:rsidRPr="004A6D87"><w:rPr><w:rFonts w:ascii="Times New Roman" w:hAnsi="Times New Roman"/><w:b/></w:rPr><w:t>Дьячук Антон Витальевич</w:t></w:r></w:fldSimple></w:p><w:p w:rsidR="00445E78" w:rsidRPr="004A6D87" w:rsidRDefault="00445E78" w:rsidP="00445E78"><w:pPr><w:rPr><w:i/><w:iCs/><w:sz w:val="20"/><w:szCs w:val="20"/></w:rPr></w:pPr><w:r w:rsidRPr="004A6D87"><w:rPr><w:i/><w:iCs/><w:sz w:val="20"/><w:szCs w:val="20"/></w:rPr><w:t xml:space="preserve">Дата рождения: </w:t></w:r><w:fldSimple w:instr=" DOCPROPERTY  birthday  \* MERGEFORMAT "><w:r w:rsidR="004A6D87" w:rsidRPr="004A6D87"><w:rPr><w:i/><w:iCs/><w:sz w:val="20"/><w:szCs w:val="20"/></w:rPr><w:t>1980-05-20</w:t></w:r></w:fldSimple></w:p><w:p w:rsidR="00445E78" w:rsidRPr="004A6D87" w:rsidRDefault="00445E78" w:rsidP="00445E78"><w:pPr><w:rPr><w:i/><w:iCs/><w:sz w:val="20"/><w:szCs w:val="20"/></w:rPr></w:pPr><w:r w:rsidRPr="004A6D87"><w:rPr><w:i/><w:iCs/><w:sz w:val="20"/><w:szCs w:val="20"/></w:rPr><w:t xml:space="preserve">Адрес: </w:t></w:r><w:fldSimple w:instr=" DOCPROPERTY  address  \* MERGEFORMAT "><w:r w:rsidR="004A6D87" w:rsidRPr="004A6D87"><w:rPr><w:i/><w:iCs/><w:sz w:val="20"/><w:szCs w:val="20"/></w:rPr><w:t>Челябинск</w:t></w:r><w:r w:rsidR="004A6D87" w:rsidRPr="004A6D87"><w:rPr><w:sz w:val="20"/><w:szCs w:val="20"/></w:rPr><w:t>, Танкистов 150-Г</w:t></w:r></w:fldSimple></w:p><w:p w:rsidR="00445E78" w:rsidRPr="004A6D87" w:rsidRDefault="00445E78" w:rsidP="00445E78"><w:pPr><w:rPr><w:i/><w:iCs/><w:sz w:val="20"/><w:szCs w:val="20"/></w:rPr></w:pPr><w:r w:rsidRPr="004A6D87"><w:rPr><w:i/><w:iCs/><w:sz w:val="20"/><w:szCs w:val="20"/></w:rPr><w:t xml:space="preserve">Паспорт </w:t></w:r><w:fldSimple w:instr=" DOCPROPERTY  p_id  \* MERGEFORMAT "><w:r w:rsidR="004A6D87" w:rsidRPr="004A6D87"><w:rPr><w:i/><w:iCs/><w:sz w:val="20"/><w:szCs w:val="20"/></w:rPr><w:t xml:space="preserve">7505 914913 УВД  </w:t></w:r><w:r w:rsidR="004A6D87" w:rsidRPr="004A6D87"><w:rPr><w:sz w:val="20"/><w:szCs w:val="20"/></w:rPr><w:t>Металлургического района г. Челябинска</w:t></w:r></w:fldSimple></w:p><w:p w:rsidR="00445E78" w:rsidRPr="00445E78" w:rsidRDefault="00445E78" w:rsidP="00445E78"><w:r w:rsidRPr="004A6D87"><w:rPr><w:i/><w:iCs/><w:sz w:val="20"/><w:szCs w:val="20"/></w:rPr><w:t xml:space="preserve">Контактный  тел.: </w:t></w:r><w:fldSimple w:instr=" DOCPROPERTY  phones  \* MERGEFORMAT "><w:r w:rsidR="004A6D87" w:rsidRPr="004A6D87"><w:rPr><w:i/><w:iCs/><w:sz w:val="20"/><w:szCs w:val="20"/></w:rPr><w:t>+7 908 815 51 07</w:t></w:r></w:fldSimple></w:p><w:p w:rsidR="00445E78" w:rsidRDefault="00445E78"><w:pPr><w:pStyle w:val="a5"/><w:rPr><w:lang w:val="en-US"/></w:rPr></w:pPr></w:p><w:p w:rsidR="00982348" w:rsidRPr="00982348" w:rsidRDefault="00982348"><w:pPr><w:pStyle w:val="a5"/><w:rPr><w:lang w:val="en-US"/></w:rPr></w:pPr></w:p><w:p w:rsidR="00445E78" w:rsidRPr="00445E78" w:rsidRDefault="00445E78" w:rsidP="00445E78"><w:pPr><w:tabs><w:tab w:val="left" w:pos="4111"/></w:tabs><w:jc w:val="both"/></w:pPr><w:r w:rsidRPr="005D01BC"><w:rPr><w:sz w:val="20"/><w:szCs w:val="20"/></w:rPr><w:t xml:space="preserve">_________________ / </w:t></w:r><w:r><w:rPr><w:sz w:val="20"/><w:szCs w:val="20"/></w:rPr><w:t>Вердыш В.В./</w:t></w:r><w:r w:rsidRPr="005D01BC"><w:rPr><w:sz w:val="20"/><w:szCs w:val="20"/><w:lang w:val="en-US"/></w:rPr><w:ptab w:relativeTo="margin" w:alignment="center" w:leader="none"/></w:r><w:r w:rsidRPr="005D01BC"><w:rPr><w:sz w:val="20"/><w:szCs w:val="20"/><w:lang w:val="en-US"/></w:rPr><w:ptab w:relativeTo="margin" w:alignment="right" w:leader="none"/></w:r><w:r><w:rPr><w:sz w:val="20"/><w:szCs w:val="20"/></w:rPr><w:t xml:space="preserve">___________________/ </w:t></w:r><w:fldSimple w:instr=" DOCPROPERTY  s_name  \* MERGEFORMAT "><w:r w:rsidR="004A6D87" w:rsidRPr="004A6D87"><w:rPr><w:sz w:val="20"/><w:szCs w:val="20"/></w:rPr><w:t>Дьячук А. В.</w:t></w:r></w:fldSimple><w:r><w:rPr><w:sz w:val="20"/><w:szCs w:val="20"/></w:rPr><w:t>/</w:t></w:r></w:p></w:ftr>